[{"id":1,"name":"Masood Ur Rehman","username":"masood123","email":"maasoodrehman@gmail.com","phone":"453453345345"},{"id":2,"name":"iqbal khan","username":"iqbal","email":"asdadad@gmail.com","phone":"345344335"},{"id":3,"name":"Clementine Bauch","username":"Samantha","email":"Nathan@yesenia.net","phone":"1-463-123-4447"},{"id":4,"name":"Patricia Lebsack","username":"Karianne","email":"Julianne.OConner@kory.org","phone":"493-170-9623 x156"},{"id":5,"name":"Chelsey Dietrich","username":"Kamren","email":"Lucio_Hettinger@annie.ca","phone":"(254)954-1289"},{"id":6,"name":"Mrs. Dennis Schulist","username":"Leopoldo_Corkery","email":"Karley_Dach@jasper.info","phone":"1-477-935-8478 x6430"},{"id":7,"name":"ddddddddddd","email":"","phone":"","image":null,"personality":""},{"id":8,"name":"dddddddddd","email":"","phone":"","image":null,"personality":""},{"id":7,"name":"dddddddddddnnnnnnnnnnnnnnnnnn","email":"","phone":"","image":null,"personality":""},{"id":8,"name":"gfhfhfghg","email":"","phone":"","image":null,"personality":""}]